README.md
setup.py
sagathon/__init__.py
sagathon.egg-info/PKG-INFO
sagathon.egg-info/SOURCES.txt
sagathon.egg-info/dependency_links.txt
sagathon.egg-info/top_level.txt
sagathon/effects/__init__.py
sagathon/effects/runners.py
sagathon/effects/types.py