Metadata-Version: 1.0
Name: sagathon
Version: 0.0.1
Summary: Redux-saga, without redux, for python
Home-page: https://github.com/francoiscampbell/sagathon.git
Author: Francois Campbell
Author-email: campbell.francois@gmail.com
License: UNKNOWN
Platform: UNKNOWN
